{
  "app_name": "Rue du Commerce",
  "handle": "com.rueducommerce.mobile",
  "version": "1.4.3",
  "report_date": "2019-01-26T13:16:00.000Z",
  "permissions": [
    "android.permission.ACCESS_COARSE_LOCATION",
    "android.permission.ACCESS_FINE_LOCATION",
    "android.permission.ACCESS_NETWORK_STATE",
    "android.permission.ACCESS_WIFI_STATE",
    "android.permission.CALL_PHONE",
    "android.permission.INTERNET",
    "android.permission.READ_APP_BADGE",
    "android.permission.READ_PHONE_STATE",
    "android.permission.WAKE_LOCK",
    "android.permission.WRITE_EXTERNAL_STORAGE",
    "com.anddoes.launcher.permission.UPDATE_COUNT",
    "com.google.android.c2dm.permission.RECEIVE",
    "com.google.android.providers.gsf.permission.READ_GSERVICES",
    "com.htc.launcher.permission.READ_SETTINGS",
    "com.htc.launcher.permission.UPDATE_SHORTCUT",
    "com.huawei.android.launcher.permission.CHANGE_BADGE",
    "com.huawei.android.launcher.permission.READ_SETTINGS",
    "com.huawei.android.launcher.permission.WRITE_SETTINGS",
    "com.majeur.launcher.permission.UPDATE_BADGE",
    "com.oppo.launcher.permission.READ_SETTINGS",
    "com.oppo.launcher.permission.WRITE_SETTINGS",
    "com.rueducommerce.mobile.permission.A4S_SEND",
    "com.rueducommerce.mobile.permission.C2D_MESSAGE",
    "com.sec.android.provider.badge.permission.READ",
    "com.sec.android.provider.badge.permission.WRITE",
    "com.sonyericsson.home.permission.BROADCAST_BADGE",
    "com.sonymobile.home.permission.PROVIDER_INSERT_BADGE"
  ],
  "trackers": [
    4,
    12,
    280,
    312,
    27,
    49,
    45
  ]
}