{
  "slug": "rockstar-games",
  "service_name": "Rockstar Games",
  "analyzed_at": "2026-07-23",
  "model": "mistral-large-latest",
  "ia_status": "ia_processed",
  "source": {
    "policy_url": "https://www.take2games.com/privacy",
    "url_source": "guessed",
    "lang": null,
    "http_status": 200,
    "content_sha256": "3ee4161de4fb7a1fbcac9a634898a90fb86561b6006b7719a67dc81faf0843b7",
    "markdown_chars": 11285
  },
  "pixel_tracking": {
    "present": false,
    "details": []
  },
  "conformity": {
    "mentions_legales": [
      {
        "id": "ml_presence",
        "label": "Présence des mentions légales",
        "status": "non_evaluable_ia",
        "quote": "",
        "quote_verified": null,
        "evaluable_by_ia": false,
        "reason": "requiert audit live"
      },
      {
        "id": "ml_editeur",
        "label": "Informations sur l'éditeur du site",
        "status": "non_evaluable_ia",
        "quote": "",
        "quote_verified": null,
        "evaluable_by_ia": false,
        "reason": "requiert audit live"
      },
      {
        "id": "ml_denomination",
        "label": "Dénomination sociale (nom/raison sociale)",
        "status": "non_indique",
        "quote": "",
        "quote_verified": null,
        "evaluable_by_ia": true
      },
      {
        "id": "ml_forme_juridique",
        "label": "Forme juridique",
        "status": "non_indique",
        "quote": "",
        "quote_verified": null,
        "evaluable_by_ia": true
      },
      {
        "id": "ml_adresse",
        "label": "Adresse de l'établissement / siège social",
        "status": "non_indique",
        "quote": "",
        "quote_verified": null,
        "evaluable_by_ia": true
      },
      {
        "id": "ml_telephone",
        "label": "Numéro de téléphone",
        "status": "non_indique",
        "quote": "",
        "quote_verified": null,
        "evaluable_by_ia": true
      },
      {
        "id": "ml_email",
        "label": "Adresse de courrier électronique",
        "status": "non_indique",
        "quote": "",
        "quote_verified": null,
        "evaluable_by_ia": true
      },
      {
        "id": "ml_hebergeur_denom",
        "label": "Hébergeur : dénomination",
        "status": "non_indique",
        "quote": "",
        "quote_verified": null,
        "evaluable_by_ia": true
      },
      {
        "id": "ml_hebergeur_adr",
        "label": "Hébergeur : adresse postale",
        "status": "non_indique",
        "quote": "",
        "quote_verified": null,
        "evaluable_by_ia": true
      },
      {
        "id": "ml_hebergeur_email",
        "label": "Hébergeur : adresse email",
        "status": "non_indique",
        "quote": "",
        "quote_verified": null,
        "evaluable_by_ia": true
      },
      {
        "id": "ml_hebergeur_tel",
        "label": "Hébergeur : numéro de téléphone",
        "status": "non_indique",
        "quote": "",
        "quote_verified": null,
        "evaluable_by_ia": true
      },
      {
        "id": "ml_directeur_pub",
        "label": "Directeur/codirecteur de la publication",
        "status": "non_indique",
        "quote": "",
        "quote_verified": null,
        "evaluable_by_ia": true
      },
      {
        "id": "ml_resp_redaction",
        "label": "Responsable de la rédaction",
        "status": "non_indique",
        "quote": "",
        "quote_verified": null,
        "evaluable_by_ia": true
      },
      {
        "id": "ml_consent_news",
        "label": "Recueil consentement newsletter",
        "status": "non_evaluable_ia",
        "quote": "",
        "quote_verified": null,
        "evaluable_by_ia": false,
        "reason": "requiert audit live"
      },
      {
        "id": "ml_consent_cookies",
        "label": "Recueil consentement cookies",
        "status": "non_evaluable_ia",
        "quote": "",
        "quote_verified": null,
        "evaluable_by_ia": false,
        "reason": "requiert audit live"
      },
      {
        "id": "ml_cgu",
        "label": "Présence des CGU (facultatif)",
        "status": "non_evaluable_ia",
        "quote": "",
        "quote_verified": null,
        "evaluable_by_ia": false,
        "reason": "requiert audit live"
      }
    ],
    "politique_donnees_personnelles": [
      {
        "id": "pdp_presence",
        "label": "Présence d'une politique de confidentialité",
        "status": "non_indique",
        "quote": "",
        "quote_verified": null,
        "evaluable_by_ia": true
      },
      {
        "id": "pdp_rt_identity",
        "label": "Identité du Responsable de Traitement",
        "status": "non_indique",
        "quote": "",
        "quote_verified": null,
        "evaluable_by_ia": true
      },
      {
        "id": "pdp_dpo",
        "label": "Coordonnées du DPO",
        "status": "non_indique",
        "quote": "",
        "quote_verified": null,
        "evaluable_by_ia": true
      },
      {
        "id": "pdp_data_types",
        "label": "Types de données collectées + raison",
        "status": "non_indique",
        "quote": "",
        "quote_verified": null,
        "evaluable_by_ia": true
      },
      {
        "id": "pdp_base_legale",
        "label": "Base légale du traitement",
        "status": "non_indique",
        "quote": "",
        "quote_verified": null,
        "evaluable_by_ia": true
      },
      {
        "id": "pdp_obligatoire",
        "label": "Caractère obligatoire/facultatif + conséquences",
        "status": "non_indique",
        "quote": "",
        "quote_verified": null,
        "evaluable_by_ia": true
      },
      {
        "id": "pdp_conservation",
        "label": "Durée de conservation des données",
        "status": "non_indique",
        "quote": "",
        "quote_verified": null,
        "evaluable_by_ia": true
      },
      {
        "id": "pdp_destinataires",
        "label": "Destinataires des données",
        "status": "non_indique",
        "quote": "",
        "quote_verified": null,
        "evaluable_by_ia": true
      },
      {
        "id": "pdp_decision_auto",
        "label": "Prise de décision automatisée",
        "status": "non_indique",
        "quote": "",
        "quote_verified": null,
        "evaluable_by_ia": true
      },
      {
        "id": "pdp_securite",
        "label": "Sécurité des données (art. 32 RGPD)",
        "status": "non_indique",
        "quote": "",
        "quote_verified": null,
        "evaluable_by_ia": true
      },
      {
        "id": "pdp_collecte_indir",
        "label": "Collecte indirecte : catégories concernées",
        "status": "non_indique",
        "quote": "",
        "quote_verified": null,
        "evaluable_by_ia": true
      },
      {
        "id": "pdp_source_indir",
        "label": "Collecte indirecte : source des données",
        "status": "non_indique",
        "quote": "",
        "quote_verified": null,
        "evaluable_by_ia": true
      },
      {
        "id": "pdp_droit_plainte",
        "label": "Droit d'introduire une plainte (CNIL)",
        "status": "non_indique",
        "quote": "",
        "quote_verified": null,
        "evaluable_by_ia": true
      },
      {
        "id": "pdp_droit_rectif",
        "label": "Droit de rectification",
        "status": "non_indique",
        "quote": "",
        "quote_verified": null,
        "evaluable_by_ia": true
      },
      {
        "id": "pdp_droit_acces",
        "label": "Droit d'accès",
        "status": "non_indique",
        "quote": "",
        "quote_verified": null,
        "evaluable_by_ia": true
      },
      {
        "id": "pdp_droit_efface",
        "label": "Droit à l'effacement",
        "status": "non_indique",
        "quote": "",
        "quote_verified": null,
        "evaluable_by_ia": true
      },
      {
        "id": "pdp_droit_limit",
        "label": "Droit à la limitation du traitement",
        "status": "non_indique",
        "quote": "",
        "quote_verified": null,
        "evaluable_by_ia": true
      },
      {
        "id": "pdp_droit_porta",
        "label": "Droit à la portabilité",
        "status": "non_indique",
        "quote": "",
        "quote_verified": null,
        "evaluable_by_ia": true
      },
      {
        "id": "pdp_droit_oppo",
        "label": "Droit d'opposition",
        "status": "non_indique",
        "quote": "",
        "quote_verified": null,
        "evaluable_by_ia": true
      },
      {
        "id": "pdp_date_maj",
        "label": "Date de dernière mise à jour de la politique",
        "status": "non_indique",
        "quote": "",
        "quote_verified": null,
        "evaluable_by_ia": true
      }
    ],
    "cookies": [
      {
        "id": "ck_presence",
        "label": "Présence d'une politique cookies",
        "status": "non_indique",
        "quote": "",
        "quote_verified": null,
        "evaluable_by_ia": true
      },
      {
        "id": "ck_consent_avant",
        "label": "Dépôt uniquement après consentement",
        "status": "non_evaluable_ia",
        "quote": "",
        "quote_verified": null,
        "evaluable_by_ia": false,
        "reason": "requiert audit live"
      },
      {
        "id": "ck_refus",
        "label": "Prise en compte du refus",
        "status": "non_evaluable_ia",
        "quote": "",
        "quote_verified": null,
        "evaluable_by_ia": false,
        "reason": "requiert audit live"
      },
      {
        "id": "ck_bandeau_neutre",
        "label": "Bandeau neutre (action positive)",
        "status": "non_evaluable_ia",
        "quote": "",
        "quote_verified": null,
        "evaluable_by_ia": false,
        "reason": "requiert audit live"
      },
      {
        "id": "ck_refus_facile",
        "label": "Refuser aussi facilement qu'accepter",
        "status": "non_evaluable_ia",
        "quote": "",
        "quote_verified": null,
        "evaluable_by_ia": false,
        "reason": "requiert audit live"
      },
      {
        "id": "ck_retrait",
        "label": "Retrait du consentement simple et à tout moment",
        "status": "non_evaluable_ia",
        "quote": "",
        "quote_verified": null,
        "evaluable_by_ia": false,
        "reason": "requiert audit live"
      },
      {
        "id": "ck_info_rt",
        "label": "Information sur le Responsable de Traitement",
        "status": "non_indique",
        "quote": "",
        "quote_verified": null,
        "evaluable_by_ia": true
      },
      {
        "id": "ck_info_finalite",
        "label": "Finalité des cookies (claire et complète)",
        "status": "non_indique",
        "quote": "",
        "quote_verified": null,
        "evaluable_by_ia": true
      },
      {
        "id": "ck_info_duree",
        "label": "Durée de conservation des cookies",
        "status": "non_indique",
        "quote": "",
        "quote_verified": null,
        "evaluable_by_ia": true
      },
      {
        "id": "ck_info_partenaires",
        "label": "Liste des partenaires à jour",
        "status": "non_indique",
        "quote": "",
        "quote_verified": null,
        "evaluable_by_ia": true
      },
      {
        "id": "ck_detail_finalites",
        "label": "Détail des finalités (2e niveau)",
        "status": "non_indique",
        "quote": "",
        "quote_verified": null,
        "evaluable_by_ia": true
      },
      {
        "id": "ck_detail_types",
        "label": "Détail des types de cookies déposés",
        "status": "non_indique",
        "quote": "",
        "quote_verified": null,
        "evaluable_by_ia": true
      },
      {
        "id": "ck_distinction",
        "label": "Distinction fonctionnels / publicitaires",
        "status": "non_indique",
        "quote": "",
        "quote_verified": null,
        "evaluable_by_ia": true
      },
      {
        "id": "ck_outil_stat",
        "label": "Outil de mesure d'audience mentionné",
        "status": "non_indique",
        "quote": "",
        "quote_verified": null,
        "evaluable_by_ia": true
      },
      {
        "id": "ck_consent_stat",
        "label": "Consentement requis pour l'outil statistique",
        "status": "non_indique",
        "quote": "",
        "quote_verified": null,
        "evaluable_by_ia": true
      }
    ],
    "transferts_hors_ue": [
      {
        "id": "tr_transfert_hors_ue",
        "label": "Existence de transferts hors UE + destinataires",
        "status": "non_indique",
        "quote": "",
        "quote_verified": null,
        "evaluable_by_ia": true
      },
      {
        "id": "tr_cloud_hors_ue",
        "label": "Stockage cloud hors UE + localisation serveurs",
        "status": "non_indique",
        "quote": "",
        "quote_verified": null,
        "evaluable_by_ia": true
      }
    ]
  },
  "review": {
    "flags": [],
    "reviewer": null,
    "reviewed_at": null,
    "notes": null
  },
  "data_inventory": {
    "inventory_analyzed_at": "2026-07-23T21:54:26.701096+00:00",
    "model": "mistral-large-latest",
    "ia_status": "needs_review",
    "categories": {
      "identite": {
        "status": "oui",
        "quote": "- **Identifiers / Contact Information**: Name, user name, gamertag, postal and email address, phone number, unique IDs, mobile device ID, platform ID, gaming service ID, advertising ID (IDFA, Android ID), and IP address\n- **Protected Characteristics**: Age and gender",
        "purpose": "Identification et personnalisation des services, vérification d'éligibilité pour promotions, support utilisateur.",
        "quote_verified": true
      },
      "contact": {
        "status": "oui",
        "quote": "- **Identifiers / Contact Information**: Name, user name, gamertag, postal and email address, phone number, unique IDs, mobile device ID, platform ID, gaming service ID, advertising ID (IDFA, Android ID), and IP address",
        "purpose": "Communication avec l'utilisateur, envoi de promotions, support et gestion des comptes.",
        "quote_verified": true
      },
      "compte_auth": {
        "status": "oui",
        "quote": "- **Sensitive Information**: account credentials (user name and password)",
        "purpose": "Authentification et gestion des comptes utilisateurs.",
        "quote_verified": false
      },
      "paiement": {
        "status": "oui",
        "quote": "- **Billing Information**: Payment information (credit / debit card information) and shipping address",
        "purpose": "Traitement des paiements et livraison des commandes.",
        "quote_verified": true
      },
      "localisation": {
        "status": "oui",
        "quote": "- **Sensitive Information**: Precise location information (if you allow the Services to collect your location)",
        "purpose": "Fournir des services basés sur la localisation si autorisé par l'utilisateur.",
        "quote_verified": true
      },
      "appareil_technique": {
        "status": "oui",
        "quote": "- **Identifiers / Contact Information**: mobile device ID, platform ID, gaming service ID, advertising ID (IDFA, Android ID), and IP address\n- **Device and Usage Data**: Device type, software and hardware details, language settings, browser type and version, operating system",
        "purpose": "Personnalisation des services, amélioration de l'expérience utilisateur et analyse technique.",
        "quote_verified": false
      },
      "usage_comportement": {
        "status": "oui",
        "quote": "- **Commercial Information**: Purchase and usage history and preferences, including gameplay information\n- **Internet / Electronic Activity**: Web / app browsing and gameplay information related to the Services; information about your online interaction(s) with the Services or our advertising; and details about the games and platforms you use and other information related to installed applications\n- **Device and Usage Data**: information about how users use and interact with the Services (e.g., content viewed, pages visited, clicks, scrolls)\n- **Profile Inferences**: Inferences made from your information and web activity to help create a personalized profile so we can identify goods and services that may be of interest",
        "purpose": "Analyse du comportement utilisateur, personnalisation des services et publicités ciblées.",
        "quote_verified": false
      },
      "contenus_utilisateur": {
        "status": "oui",
        "quote": "- **Audio / Visual Information**: Account photos, images, and avatars, audio information via chat features and functionality, and gameplay recordings and video footage (such as when you participate in playtesting)",
        "purpose": "Gestion des contenus créés par l'utilisateur (avatars, enregistrements de gameplay, chats).",
        "quote_verified": true
      },
      "communications": {
        "status": "oui",
        "quote": "- **Sensitive Information**: contents of communications via chat features and functionality",
        "purpose": "Gestion des communications entre utilisateurs (chats, messages).",
        "quote_verified": false
      },
      "contacts_reseau": {
        "status": "non",
        "quote": "",
        "purpose": "Non mentionné dans la politique.",
        "quote_verified": null
      },
      "donnees_tiers": {
        "status": "oui",
        "quote": "- from third parties, such as advertising networks, business partners, third party information providers, and other players",
        "purpose": "Collecte de données via des tiers pour la publicité, les partenariats et l'amélioration des services.",
        "quote_verified": true
      },
      "biometrie": {
        "status": "non",
        "quote": "",
        "purpose": "Non mentionné dans la politique.",
        "quote_verified": null
      },
      "donnees_sensibles": {
        "status": "oui",
        "quote": "- **Sensitive Information**: Precise location information (if you allow the Services to collect your location), account credentials (user name and password), contents of communications via chat features and functionality, government identification (as reasonably necessary or required by law, e.g., to verify winner eligibility for promotional prizes)",
        "purpose": "Gestion des données sensibles comme la localisation précise, les identifiants de compte et les communications.",
        "quote_verified": true
      },
      "mineurs": {
        "status": "oui",
        "quote": "- **Sensitive Information**: personal information from children under 13 (or older, if applicable law provides for different protections)",
        "purpose": "Collecte limitée et encadrée des données des mineurs, avec consentement parental si nécessaire.",
        "quote_verified": false
      },
      "autre": {
        "status": "non",
        "quote": "",
        "purpose": "Aucune donnée non classable identifiée.",
        "quote_verified": null
      }
    },
    "legal_bases": [
      {
        "basis": "contrat",
        "data": "Identifiers / Contact Information, Billing Information, Device and Usage Data, Account credentials",
        "quote": "- Business Purposes: Provide the Services and support; fulfill orders and requests",
        "quote_verified": true
      },
      {
        "basis": "interet_legitime",
        "data": "Identifiers / Contact Information, Internet / Electronic Activity, Device and Usage Data, Profile Inferences",
        "quote": "- Business Purposes: improve the Services and our business; develop new products and services; enhance your experience on the Services; protect the security for our users, employees, facilities, and Services; and develop internal marketing and demographic studies",
        "quote_verified": false
      },
      {
        "basis": "consentement",
        "data": "Precise location information, personal information from children under 13 (or older)",
        "quote": "- **Sensitive Information**: Precise location information (if you allow the Services to collect your location)\n- We may direct certain Services to an audience of all ages---including children. For these Services, we may restrict the collection of personal information on the Services from anyone, apply an age gate allowing children to use the Services while restricting the collection of personal information on the Services from children, or get a parent's permission to collect personal information from children.",
        "quote_verified": false
      },
      {
        "basis": "obligation_legale",
        "data": "Government identification, personal information (as required by law)",
        "quote": "- **Sensitive Information**: government identification (as reasonably necessary or required by law, e.g., to verify winner eligibility for promotional prizes)\n- We also use your information as permitted or required by law.",
        "quote_verified": false
      },
      {
        "basis": "consentement",
        "data": "Internet / Electronic Activity, Profile Inferences (for targeted advertising)",
        "quote": "- Commercial Purposes: Market and advertise our and our business partners' products and services; send you promotional materials; and administer promotional activities or events\n- In the last 12 months, Take-Two has sold and/or shared unique identifiers, IP address, as well as Internet/Electronic Activity and Profile Inferences with third-party advertising providers to enable us to provide personalized advertising to you and others like you.",
        "quote_verified": false
      }
    ],
    "transfers": {
      "outside_eu": "oui",
      "countries": [
        "United States"
      ],
      "quote": "- We and our vendors and partners may process, transfer, and store information about you in connection with the Services in the United States and other countries that may not have privacy laws equivalent to the country where you reside.",
      "quote_verified": false
    },
    "data_score": {
      "weighted": 19,
      "raw_count": 12,
      "sensitive_count": 2
    }
  }
}
