{
  "name": "Happn",
  "logo": "https://upload.wikimedia.org/wikipedia/fr/1/1f/Logo_Happn_2023.svg",
  "nationality": "Chinoise",
  "country_name": "China",
  "country_code": "cn",
  "belongs_to_group": true,
  "group_name": "Hello group",
  "permissions": "",
  "contact_mail_export": "dpo@happn.fr",
  "easy_access_data": "4",
  "need_id_card": true,
  "confidentiality_policy_url": "https://support.happn.fr/hc/fr/p/privacy",
  "confidentiality_policy_url_en": "https://support.happn.fr/hc/en-us/p/privacy",
  "data_access_via_postal": true,
  "data_access_via_form": false,
  "data_access_via_email": true,
  "response_format": "",
  "example_data_export": [],
  "example_form_export": [],
  "message_exchange": [],
  "url_export": "",
  "address_export": "5 rue Feydeau  75002 Paris – France",
  "response_delay": "",
  "sanctioned_by_cnil": false,
  "sanction_details": "",
  "data_transfer_policy": true,
  "privacy_policy_quote": "Les données personnelles des Membres traitées dans le cadre de l’utilisation de l’Application sont hébergées dans l’Union européenne. \n Toutefois, les données personnelles des Membres sont transmises à des prestataires sous-traitants de HAPPN situés hors Union européenne, pour le support aux Membres, la gestion des signalements, la publicité et le marketing. \n Les transferts de données hors Union européenne peuvent être effectués vers des pays pour lesquels il n’existe pas de décision d’adéquation rendue par la Commission européenne en matière de protection des données personnelles.",
  "transfer_destination_countries": "États-Unis, Maroc, Euurope, Madagascar ",
  "transfer_destination_countries_en": "United States, Morocco, Europe, Madagascar",
  "outside_eu_storage": false,
  "comments": "Lien vers la liste des sous-traitants : https://support.happn.fr/hc/fr/p/data-recipients",
  "comments_en": "Link to the list of subcontractors : https://support.happn.fr/hc/fr/p/data-recipients",
  "tosdr": "",
  "exodus": "/data/compare/happn.json",
  "created_at": "2026-02-15",
  "created_by": "Rokiatou",
  "updated_at": "",
  "updated_by": "",
  "app": {
    "name": "Happn : appli de rencontre",
    "link": "https://play.google.com/store/apps/details?id=com.ftw_and_co.happn"
  },
  "alternatives": [
    "tinder",
    "bumble"
  ]
}
